whatimage/__init__.py
whatimage/image_format.py
whatimage/isobmff_formats.py
whatimage/simple_formats.py
whatimage-0.0.3.dist-info/LICENSE
whatimage-0.0.3.dist-info/METADATA
whatimage-0.0.3.dist-info/WHEEL
whatimage-0.0.3.dist-info/top_level.txt
whatimage-0.0.3.dist-info/RECORD
